benchmarks/__init__.py
benchmarks/load_test.py
benchmarks/memory_profile.py
benchmarks/performance_test.py
entropic_core/__init__.py
entropic_core/brain.py
entropic_core/cli.py
entropic_core/config.py
entropic_core/quickstart.py
entropic_core/advanced/__init__.py
entropic_core/advanced/causal_analyzer.py
entropic_core/advanced/predictive_engine.py
entropic_core/advanced/security_layer.py
entropic_core/advanced/simulation_mode.py
entropic_core/business/__init__.py
entropic_core/business/metrics.py
entropic_core/conversion/__init__.py
entropic_core/conversion/converter.py
entropic_core/conversion/tracker.py
entropic_core/core/__init__.py
entropic_core/core/active_intervention.py
entropic_core/core/agent_adapter.py
entropic_core/core/auto_healer.py
entropic_core/core/consensus_engine.py
entropic_core/core/entropy_monitor.py
entropic_core/core/entropy_regulator.py
entropic_core/core/evolutionary_memory.py
entropic_core/core/hallucination_detector.py
entropic_core/core/llm_middleware.py
entropic_core/diagnosis/__init__.py
entropic_core/diagnosis/diagnostic_scripts.py
entropic_core/diagnosis/problem_detector.py
entropic_core/discovery/__init__.py
entropic_core/discovery/auto_discover.py
entropic_core/discovery/llm_discoverer.py
entropic_core/discovery/setup_wizard.py
entropic_core/enterprise/__init__.py
entropic_core/enterprise/compliance.py
entropic_core/enterprise/marketplace.py
entropic_core/enterprise/orchestrator.py
entropic_core/enterprise/report_generator.py
entropic_core/i18n/__init__.py
entropic_core/i18n/translations.py
entropic_core/integrations/__init__.py
entropic_core/integrations/autogen_adapter.py
entropic_core/integrations/crewai_adapter.py
entropic_core/integrations/custom_builder.py
entropic_core/integrations/langchain_adapter.py
entropic_core/integrations/vercel_ai_adapter.py
entropic_core/messaging/__init__.py
entropic_core/messaging/messages.py
entropic_core/optimization/__init__.py
entropic_core/optimization/async_operations.py
entropic_core-4.0.0.dist-info/licenses/LICENSE
entropic_core-4.0.0.dist-info/METADATA
entropic_core-4.0.0.dist-info/WHEEL
entropic_core-4.0.0.dist-info/entry_points.txt
entropic_core-4.0.0.dist-info/top_level.txt
entropic_core-4.0.0.dist-info/RECORD
