Metadata-Version: 2.4
Name: entropic-core
Version: 4.0.0
Summary: Privacy-first entropy monitoring with active LLM intervention for multi-agent systems
Home-page: https://github.com/entropic-core/entropic-core
Author: Entropic Core Team
Author-email: info@entropic-core.com
Project-URL: Bug Reports, https://github.com/entropic-core/entropic-core/issues
Project-URL: Source, https://github.com/entropic-core/entropic-core
Project-URL: Documentation, https://entropic-core.readthedocs.io
Project-URL: Discord, https://discord.gg/entropic-core
Project-URL: Privacy Policy, https://github.com/entropic-core/entropic-core/blob/main/PRIVACY.md
Keywords: ai agents multi-agent entropy regulation homeostasis machine-learning hallucination-detection privacy-first
Classifier: Development Status :: 4 - Beta
Classifier: Intended Audience :: Developers
Classifier: Topic :: Software Development :: Libraries :: Python Modules
Classifier: Topic :: Scientific/Engineering :: Artificial Intelligence
Classifier: License :: OSI Approved :: MIT License
Classifier: Programming Language :: Python :: 3
Classifier: Programming Language :: Python :: 3.8
Classifier: Programming Language :: Python :: 3.9
Classifier: Programming Language :: Python :: 3.10
Classifier: Programming Language :: Python :: 3.11
Classifier: Operating System :: OS Independent
Requires-Python: >=3.8
License-File: LICENSE
Requires-Dist: numpy>=1.20.0
Requires-Dist: typing-extensions>=4.0.0
Requires-Dist: requests>=2.25.0
Requires-Dist: click>=8.0.0
Provides-Extra: analytics
Requires-Dist: scipy>=1.7.0; extra == "analytics"
Requires-Dist: scikit-learn>=1.0.0; extra == "analytics"
Provides-Extra: visualization
Requires-Dist: flask>=2.0.0; extra == "visualization"
Requires-Dist: flask-cors>=3.0.0; extra == "visualization"
Requires-Dist: plotly>=5.0.0; extra == "visualization"
Requires-Dist: pandas>=1.3.0; extra == "visualization"
Provides-Extra: reports
Requires-Dist: reportlab>=3.6.0; extra == "reports"
Provides-Extra: streaming
Requires-Dist: websockets>=10.0; extra == "streaming"
Requires-Dist: aiohttp>=3.8.0; extra == "streaming"
Provides-Extra: full
Requires-Dist: scipy>=1.7.0; extra == "full"
Requires-Dist: scikit-learn>=1.0.0; extra == "full"
Requires-Dist: flask>=2.0.0; extra == "full"
Requires-Dist: flask-cors>=3.0.0; extra == "full"
Requires-Dist: plotly>=5.0.0; extra == "full"
Requires-Dist: pandas>=1.3.0; extra == "full"
Requires-Dist: reportlab>=3.6.0; extra == "full"
Requires-Dist: websockets>=10.0; extra == "full"
Requires-Dist: aiohttp>=3.8.0; extra == "full"
Requires-Dist: pyyaml>=6.0.3; extra == "full"
Requires-Dist: psutil>=7.2.1; extra == "full"
Requires-Dist: redis>=7.1.0; extra == "full"
Provides-Extra: dev
Requires-Dist: pytest>=7.0.0; extra == "dev"
Requires-Dist: pytest-cov>=3.0.0; extra == "dev"
Requires-Dist: pytest-asyncio>=0.20.0; extra == "dev"
Requires-Dist: black>=22.0.0; extra == "dev"
Requires-Dist: flake8>=4.0.0; extra == "dev"
Requires-Dist: mypy>=0.950; extra == "dev"
Dynamic: author
Dynamic: author-email
Dynamic: classifier
Dynamic: description
Dynamic: description-content-type
Dynamic: home-page
Dynamic: keywords
Dynamic: license-file
Dynamic: project-url
Dynamic: provides-extra
Dynamic: requires-dist
Dynamic: requires-python
Dynamic: summary
